talisman_tools/__init__.py
talisman_tools/__main__.py
talisman_tools/parser_helper.py
talisman_tools/talisman.py
talisman_tools/talisman_logging.py
talisman_tools/arguments/__init__.py
talisman_tools/arguments/domain.py
talisman_tools/arguments/processor.py
talisman_tools/arguments/reader.py
talisman_tools/arguments/serializer.py
talisman_tools/commands/__init__.py
talisman_tools/commands/subparsers.py
talisman_tools/commands/dataset/__init__.py
talisman_tools/commands/dataset/parser.py
talisman_tools/commands/dataset/commands/__init__.py
talisman_tools/commands/dataset/commands/subparsers.py
talisman_tools/commands/dataset/commands/convert/__init__.py
talisman_tools/commands/dataset/commands/convert/parser.py
talisman_tools/commands/model/__init__.py
talisman_tools/commands/model/parser.py
talisman_tools/commands/model/commands/__init__.py
talisman_tools/commands/model/commands/subparsers.py
talisman_tools/commands/model/commands/check_performance/__init__.py
talisman_tools/commands/model/commands/check_performance/action.py
talisman_tools/commands/model/commands/check_performance/parser.py
talisman_tools/commands/model/commands/configure/__init__.py
talisman_tools/commands/model/commands/configure/parser.py
talisman_tools/commands/model/commands/evaluate/__init__.py
talisman_tools/commands/model/commands/evaluate/action.py
talisman_tools/commands/model/commands/evaluate/evaluation.py
talisman_tools/commands/model/commands/evaluate/helpers.py
talisman_tools/commands/model/commands/evaluate/metrics.py
talisman_tools/commands/model/commands/evaluate/parser.py
talisman_tools/commands/model/commands/evaluate/evaluators/__init__.py
talisman_tools/commands/model/commands/evaluate/evaluators/disambiguation_quality.py
talisman_tools/commands/model/commands/evaluate/evaluators/nerc.py
talisman_tools/commands/model/commands/evaluate/evaluators/relext.py
talisman_tools/commands/model/commands/process/__init__.py
talisman_tools/commands/model/commands/process/action.py
talisman_tools-0.11.1.dist-info/METADATA
talisman_tools-0.11.1.dist-info/WHEEL
talisman_tools-0.11.1.dist-info/entry_points.txt
talisman_tools-0.11.1.dist-info/top_level.txt
talisman_tools-0.11.1.dist-info/RECORD
