Metadata-Version: 2.4
Name: talisman-tools
Version: 0.11.1
Summary: Talisman applications
Author: ISPRAS Talisman NLP team
Author-email: modis@ispras.ru
Maintainer: Vladimir Mayorov
Maintainer-email: vmayorov@ispras.ru
License: Apache Software License
Classifier: Development Status :: 3 - Alpha
Classifier: Programming Language :: Python :: 3
Classifier: Programming Language :: Python :: 3.10
Classifier: Intended Audience :: Developers
Classifier: Operating System :: OS Independent
Classifier: License :: OSI Approved :: Apache Software License
Requires-Python: >=3.10
Requires-Dist: talisman-interfaces<0.12,>=0.11.1
Requires-Dist: talisman-dm<2,>=1.3.1
Requires-Dist: fastapi>=0.73.0
Requires-Dist: pydantic~=2.5
Requires-Dist: uvicorn>=0.13.3
Requires-Dist: requests~=2.31
Requires-Dist: urllib3~=2.2
Requires-Dist: jsonformatter>=0.3.0
Requires-Dist: starlette
Requires-Dist: anyio
Requires-Dist: pyyaml
Provides-Extra: logstash
Requires-Dist: python3-logstash>=0.4.80; extra == "logstash"
Provides-Extra: evaluate
Requires-Dist: numpy; extra == "evaluate"
Requires-Dist: scipy; extra == "evaluate"
Requires-Dist: typing_extensions~=4.8.0; extra == "evaluate"
Provides-Extra: cuda-metrics
Requires-Dist: torch; extra == "cuda-metrics"
Provides-Extra: tests
Requires-Dist: parameterized~=0.9.0; extra == "tests"
Dynamic: author
Dynamic: author-email
Dynamic: classifier
Dynamic: description-content-type
Dynamic: license
Dynamic: maintainer
Dynamic: maintainer-email
Dynamic: provides-extra
Dynamic: requires-dist
Dynamic: requires-python
Dynamic: summary
